README.md
setup.py
src/file_manager/__init__.py
src/file_manager/exception.py
src/file_manager/database_manager/__init__.py
src/file_manager/database_manager/databasemanager.py
src/file_manager/private_repo/__init__.py
src/file_manager/private_repo/_file_manager_api.py
src/file_manager/private_repo/_file_manager_csv.py
src/file_manager/private_repo/_file_manager_json.py
src/file_manager/private_repo/_file_manager_sqlite.py
src/file_manager/public/__init__.py
src/file_manager/public/file_manager_base.py
src/file_manager/public/file_manager_factory.py
src/vic_data_science.egg-info/PKG-INFO
src/vic_data_science.egg-info/SOURCES.txt
src/vic_data_science.egg-info/dependency_links.txt
src/vic_data_science.egg-info/top_level.txt