Metadata-Version: 2.1
Name: vic-data-science
Version: 0.1.6
Summary: Manages data by converting them to dataframes
Home-page: UNKNOWN
Author: vicLim88 (Vic Lim)
Author-email: <vic.lim@icloud.com>
License: UNKNOWN
Keywords: python,data science
Platform: UNKNOWN
Classifier: Development Status :: 1 - Planning
Classifier: Intended Audience :: Developers
Classifier: Programming Language :: Python :: 3
Classifier: Operating System :: Unix
Classifier: Operating System :: MacOS :: MacOS X
Classifier: Operating System :: Microsoft :: Windows
